{
  "box": {
    "batting": {
      "ftxbf1wj156q30wd": [
        {
          "AB": 6,
          "AVG": ".362",
          "BB": 1,
          "H": 5,
          "LOB": 0,
          "R": 3,
          "RBI": 3,
          "SO": 0,
          "player_id": "2oyr5r7opv23s3pv",
          "pos": "cf"
        },
        {
          "AB": 7,
          "AVG": ".333",
          "BB": 0,
          "H": 4,
          "LOB": 0,
          "R": 2,
          "RBI": 3,
          "SO": 2,
          "player_id": "fed90noy2ji0f5sl",
          "pos": "3b"
        },
        {
          "AB": 5,
          "AVG": ".332",
          "BB": 1,
          "H": 3,
          "LOB": 4,
          "R": 2,
          "RBI": 1,
          "SO": 0,
          "player_id": "u2qlqon19x6c6w3h",
          "pos": "2b"
        },
        {
          "AB": 6,
          "AVG": ".320",
          "BB": 0,
          "H": 1,
          "LOB": 0,
          "R": 0,
          "RBI": 1,
          "SO": 1,
          "player_id": "al2kh9h54j8prr0q",
          "pos": "1b/dh"
        },
        {
          "AB": 5,
          "AVG": ".358",
          "BB": 1,
          "H": 1,
          "LOB": 2,
          "R": 1,
          "RBI": 0,
          "SO": 0,
          "player_id": "3lh7rsmeoi2aw47t",
          "pos": "dh/lf"
        },
        {
          "AB": 5,
          "AVG": ".286",
          "BB": 1,
          "H": 2,
          "LOB": 4,
          "R": 2,
          "RBI": 1,
          "SO": 0,
          "player_id": "hq3sxg95w4ouku79",
          "pos": "rf"
        },
        {
          "AB": 6,
          "AVG": ".266",
          "BB": 0,
          "H": 3,
          "LOB": 0,
          "R": 1,
          "RBI": 2,
          "SO": 0,
          "player_id": "yh45rm8iw5xetrej",
          "pos": "c"
        },
        {
          "AB": 0,
          "AVG": ".194",
          "BB": 0,
          "H": 0,
          "LOB": 0,
          "R": 0,
          "RBI": 0,
          "SO": 0,
          "player_id": "q2ilr80howzzuw5j",
          "pos": "pr"
        },
        {
          "AB": 4,
          "AVG": ".250",
          "BB": 0,
          "H": 1,
          "LOB": 3,
          "R": 2,
          "RBI": 2,
          "SO": 1,
          "player_id": "b0wcwq9r4nvqldwt",
          "pos": "lf/1b"
        },
        {
          "AB": 6,
          "AVG": ".226",
          "BB": 0,
          "H": 4,
          "LOB": 0,
          "R": 3,
          "RBI": 0,
          "SO": 2,
          "player_id": "wclemxwmo2sy8wth",
          "pos": "ss"
        },
        {
          "AB": 0,
          "AVG": "0",
          "BB": 0,
          "H": 0,
          "LOB": 0,
          "R": 0,
          "RBI": 0,
          "SO": 0,
          "player_id": "pc4t8yra3oyd3bcw",
          "pos": "p"
        },
        {
          "AB": 0,
          "AVG": "0",
          "BB": 0,
          "H": 0,
          "LOB": 0,
          "R": 0,
          "RBI": 0,
          "SO": 0,
          "player_id": "khcrwbcbipu2bcmg",
          "pos": "p"
        },
        {
          "AB": 0,
          "AVG": "0",
          "BB": 0,
          "H": 0,
          "LOB": 0,
          "R": 0,
          "RBI": 0,
          "SO": 0,
          "player_id": "riant5z354rgz3ls",
          "pos": "p"
        },
        {
          "AB": 0,
          "AVG": "0",
          "BB": 0,
          "H": 0,
          "LOB": 0,
          "R": 0,
          "RBI": 0,
          "SO": 0,
          "player_id": "2cmabhil7jgmm6c7",
          "pos": "p"
        },
        {
          "AB": 0,
          "AVG": ".000",
          "BB": 0,
          "H": 0,
          "LOB": 0,
          "R": 0,
          "RBI": 0,
          "SO": 0,
          "player_id": "1pk8u7yvk69kp4tb",
          "pos": "p"
        }
      ],
      "mw5jz3z05tswxa8m": [
        {
          "AB": 6,
          "AVG": ".342",
          "BB": 1,
          "H": 3,
          "LOB": 1,
          "R": 4,
          "RBI": 2,
          "SO": 1,
          "player_id": "zhwvtt83h5dg97d9",
          "pos": "2b"
        },
        {
          "AB": 5,
          "AVG": ".382",
          "BB": 0,
          "H": 3,
          "LOB": 0,
          "R": 3,
          "RBI": 0,
          "SO": 1,
          "player_id": "dys9nwsovxppppru",
          "pos": "rf"
        },
        {
          "AB": 5,
          "AVG": ".338",
          "BB": 1,
          "H": 3,
          "LOB": 0,
          "R": 3,
          "RBI": 7,
          "SO": 1,
          "player_id": "i2n256ipvurz082x",
          "pos": "c"
        },
        {
          "AB": 5,
          "AVG": ".403",
          "BB": 1,
          "H": 1,
          "LOB": 0,
          "R": 1,
          "RBI": 2,
          "SO": 0,
          "player_id": "ov202no2zh1hpe7l",
          "pos": "lf"
        },
        {
          "AB": 5,
          "AVG": ".323",
          "BB": 1,
          "H": 1,
          "LOB": 4,
          "R": 1,
          "RBI": 0,
          "SO": 1,
          "player_id": "gj6w3ztw7zlm4y7g",
          "pos": "dh"
        },
        {
          "AB": 4,
          "AVG": ".303",
          "BB": 2,
          "H": 2,
          "LOB": 0,
          "R": 1,
          "RBI": 1,
          "SO": 2,
          "player_id": "ldy96obdqz56e59r",
          "pos": "cf"
        },
        {
          "AB": 1,
          "AVG": ".283",
          "BB": 2,
          "H": 1,
          "LOB": 0,
          "R": 1,
          "RBI": 1,
          "SO": 0,
          "player_id": "kriqcbrfzfr25mz8",
          "pos": "ss"
        },
        {
          "AB": 2,
          "AVG": ".235",
          "BB": 1,
          "H": 1,
          "LOB": 0,
          "R": 1,
          "RBI": 1,
          "SO": 0,
          "player_id": "uo4zsqqzhrhala5g",
          "pos": "ss"
        },
        {
          "AB": 4,
          "AVG": ".224",
          "BB": 1,
          "H": 1,
          "LOB": 0,
          "R": 0,
          "RBI": 0,
          "SO": 0,
          "player_id": "3vg4tjj6lny5kazm",
          "pos": "1b"
        },
        {
          "AB": 1,
          "AVG": ".354",
          "BB": 0,
          "H": 0,
          "LOB": 0,
          "R": 0,
          "RBI": 0,
          "SO": 1,
          "player_id": "larymvbb4jx0h5i5",
          "pos": "1b"
        },
        {
          "AB": 5,
          "AVG": ".315",
          "BB": 1,
          "H": 2,
          "LOB": 5,
          "R": 2,
          "RBI": 1,
          "SO": 0,
          "player_id": "7hawkykz292el0ws",
          "pos": "3b"
        },
        {
          "AB": 0,
          "AVG": "0",
          "BB": 0,
          "H": 0,
          "LOB": 0,
          "R": 0,
          "RBI": 0,
          "SO": 0,
          "player_id": "9oiv9xmbzm3nbrir",
          "pos": "p"
        },
        {
          "AB": 0,
          "AVG": "0",
          "BB": 0,
          "H": 0,
          "LOB": 0,
          "R": 0,
          "RBI": 0,
          "SO": 0,
          "player_id": "ye2uv5q9ocw9kc31",
          "pos": "p"
        },
        {
          "AB": 0,
          "AVG": "0",
          "BB": 0,
          "H": 0,
          "LOB": 0,
          "R": 0,
          "RBI": 0,
          "SO": 0,
          "player_id": "y3vuu7pdahey0f27",
          "pos": "p"
        },
        {
          "AB": 0,
          "AVG": "0",
          "BB": 0,
          "H": 0,
          "LOB": 0,
          "R": 0,
          "RBI": 0,
          "SO": 0,
          "player_id": "256j63mgeotlic6q",
          "pos": "p"
        },
        {
          "AB": 0,
          "AVG": "0",
          "BB": 0,
          "H": 0,
          "LOB": 0,
          "R": 0,
          "RBI": 0,
          "SO": 0,
          "player_id": "l598fosvptezoca1",
          "pos": "p"
        },
        {
          "AB": 0,
          "AVG": "0",
          "BB": 0,
          "H": 0,
          "LOB": 0,
          "R": 0,
          "RBI": 0,
          "SO": 0,
          "player_id": "0og3efda00vmey7r",
          "pos": "p"
        },
        {
          "AB": 0,
          "AVG": "0",
          "BB": 0,
          "H": 0,
          "LOB": 0,
          "R": 0,
          "RBI": 0,
          "SO": 0,
          "player_id": "3ntziz6um92c2z1f",
          "pos": "p"
        }
      ]
    },
    "pitching": {
      "ftxbf1wj156q30wd": [
        {
          "BB": 5,
          "ER": 7,
          "H": 11,
          "IP": "4.0",
          "R": 9,
          "SO": 1,
          "player_id": "pc4t8yra3oyd3bcw"
        },
        {
          "BB": 2,
          "ER": 4,
          "H": 3,
          "IP": "1.0",
          "R": 4,
          "SO": 1,
          "player_id": "khcrwbcbipu2bcmg"
        },
        {
          "BB": 1,
          "ER": 1,
          "H": 1,
          "IP": "1.0",
          "R": 1,
          "SO": 2,
          "player_id": "riant5z354rgz3ls"
        },
        {
          "BB": 2,
          "ER": 2,
          "H": 2,
          "IP": "2.0",
          "R": 2,
          "SO": 1,
          "player_id": "2cmabhil7jgmm6c7"
        },
        {
          "BB": 1,
          "ER": 1,
          "H": 1,
          "IP": "1.0",
          "R": 1,
          "SO": 2,
          "player_id": "1pk8u7yvk69kp4tb"
        }
      ],
      "mw5jz3z05tswxa8m": [
        {
          "BB": 2,
          "ER": 6,
          "H": 8,
          "IP": "1.0",
          "R": 6,
          "SO": 2,
          "player_id": "9oiv9xmbzm3nbrir"
        },
        {
          "BB": 1,
          "ER": 3,
          "H": 1,
          "IP": "1.2",
          "R": 3,
          "SO": 1,
          "player_id": "ye2uv5q9ocw9kc31"
        },
        {
          "BB": 0,
          "ER": 3,
          "H": 9,
          "IP": "1.1",
          "R": 4,
          "SO": 0,
          "player_id": "y3vuu7pdahey0f27"
        },
        {
          "BB": 1,
          "ER": 1,
          "H": 3,
          "IP": "2.0",
          "R": 1,
          "SO": 1,
          "player_id": "256j63mgeotlic6q"
        },
        {
          "BB": 0,
          "ER": 2,
          "H": 2,
          "IP": "1.0",
          "R": 2,
          "SO": 0,
          "player_id": "l598fosvptezoca1"
        },
        {
          "BB": 0,
          "ER": 0,
          "H": 1,
          "IP": "0.2",
          "R": 0,
          "SO": 0,
          "player_id": "0og3efda00vmey7r"
        },
        {
          "BB": 0,
          "ER": 0,
          "H": 0,
          "IP": "1.1",
          "R": 0,
          "SO": 2,
          "player_id": "3ntziz6um92c2z1f"
        }
      ]
    }
  },
  "date": "2025-08-17",
  "events": [
    {
      "batting_team": "mw5jz3z05tswxa8m",
      "fielding_team": "ftxbf1wj156q30wd",
      "half": "top",
      "inning": 1,
      "kind": "inning_summary",
      "narrative": "Inning Summary: 4 Runs, 4 Hits, 0 Errors, 2 LOB",
      "scoring_play": false,
      "seq": 0,
      "summary": {
        "E": 0,
        "H": 4,
        "LOB": 2,
        "R": 4
      }
    },
    {
      "batting_team": "ftxbf1wj156q30wd",
      "fielding_team": "mw5jz3z05tswxa8m",
      "half": "bottom",
      "inning": 1,
      "kind": "inning_summary",
      "narrative": "Inning Summary: 4 Runs, 5 Hits, 0 Errors, 1 LOB",
      "scoring_play": false,
      "seq": 1,
      "summary": {
        "E": 0,
        "H": 5,
        "LOB": 1,
        "R": 4
      }
    },
    {
      "_derived": {
        "away_score_before": 0,
        "base_out_state": "000|0",
        "bases_after": [
          false,
          false,
          false
        ],
        "bases_before": [
          false,
          false,
          false
        ],
        "home_score_before": 0,
        "outs_after": 1,
        "outs_before": 0,
        "runs_on_play": 0
      },
      "batting_team": "mw5jz3z05tswxa8m",
      "fielding_team": "ftxbf1wj156q30wd",
      "half": "top",
      "inning": 2,
      "kind": "runner_event",
      "narrative": "C. Gordon out at second p to 2b, picked off.",
      "runners": [
        {
          "cause": "force_out",
          "from": 2,
          "out": true,
          "player_id": "gj6w3ztw7zlm4y7g",
          "scored": false,
          "to": 2
        }
      ],
      "scoring_play": false,
      "seq": 2
    },
    {
      "batting_team": "mw5jz3z05tswxa8m",
      "fielding_team": "ftxbf1wj156q30wd",
      "half": "top",
      "inning": 2,
      "kind": "inning_summary",
      "narrative": "Inning Summary: 2 Runs, 3 Hits, 0 Errors, 2 LOB",
      "scoring_play": false,
      "seq": 3,
      "summary": {
        "E": 0,
        "H": 3,
        "LOB": 2,
        "R": 2
      }
    },
    {
      "batting_team": "ftxbf1wj156q30wd",
      "fielding_team": "mw5jz3z05tswxa8m",
      "half": "bottom",
      "inning": 2,
      "kind": "substitution",
      "narrative": "A. Armstrong to p for D. Day.",
      "scoring_play": false,
      "seq": 4,
      "substitution": {
        "after_event_seq": 3,
        "kind": "pitching",
        "player_in": "ye2uv5q9ocw9kc31",
        "player_out": "9oiv9xmbzm3nbrir",
        "slot": null
      }
    },
    {
      "batting_team": "ftxbf1wj156q30wd",
      "fielding_team": "mw5jz3z05tswxa8m",
      "half": "bottom",
      "inning": 2,
      "kind": "inning_summary",
      "narrative": "Inning Summary: 2 Runs, 3 Hits, 0 Errors, 2 LOB",
      "scoring_play": false,
      "seq": 5,
      "summary": {
        "E": 0,
        "H": 3,
        "LOB": 2,
        "R": 2
      }
    },
    {
      "batting_team": "mw5jz3z05tswxa8m",
      "fielding_team": "ftxbf1wj156q30wd",
      "half": "top",
      "inning": 3,
      "kind": "inning_summary",
      "narrative": "Inning Summary: 3 Runs, 3 Hits, 1 Errors, 2 LOB",
      "scoring_play": false,
      "seq": 6,
      "summary": {
        "E": 1,
        "H": 3,
        "LOB": 2,
        "R": 3
      }
    },
    {
      "batting_team": "ftxbf1wj156q30wd",
      "fielding_team": "mw5jz3z05tswxa8m",
      "half": "bottom",
      "inning": 3,
      "kind": "substitution",
      "narrative": "R. Fields to p for A. Armstrong.",
      "scoring_play": false,
      "seq": 7,
      "substitution": {
        "after_event_seq": 6,
        "kind": "pitching",
        "player_in": "y3vuu7pdahey0f27",
        "player_out": "ye2uv5q9ocw9kc31",
        "slot": null
      }
    },
    {
      "_derived": {
        "away_score_before": 0,
        "base_out_state": "000|0",
        "bases_after": [
          false,
          false,
          true
        ],
        "bases_before": [
          false,
          false,
          false
        ],
        "home_score_before": 0,
        "outs_after": 0,
        "outs_before": 0,
        "runs_on_play": 0
      },
      "batting_team": "ftxbf1wj156q30wd",
      "fielding_team": "mw5jz3z05tswxa8m",
      "half": "bottom",
      "inning": 3,
      "kind": "runner_event",
      "narrative": "K. Moody advanced to third on a wild pitch.",
      "runners": [
        {
          "cause": "wild_pitch",
          "from": 3,
          "out": false,
          "player_id": "u2qlqon19x6c6w3h",
          "scored": false,
          "to": 3
        }
      ],
      "scoring_play": false,
      "seq": 8
    },
    {
      "batting_team": "ftxbf1wj156q30wd",
      "fielding_team": "mw5jz3z05tswxa8m",
      "half": "bottom",
      "inning": 3,
      "kind": "inning_summary",
      "narrative": "Inning Summary: 4 Runs, 4 Hits, 0 Errors, 2 LOB",
      "scoring_play": false,
      "seq": 9,
      "summary": {
        "E": 0,
        "H": 4,
        "LOB": 2,
        "R": 4
      }
    },
    {
      "_derived": {
        "away_score_before": 0,
        "base_out_state": "000|0",
        "bases_after": [
          false,
          true,
          false
        ],
        "bases_before": [
          false,
          false,
          false
        ],
        "home_score_before": 0,
        "outs_after": 1,
        "outs_before": 0,
        "runs_on_play": 0
      },
      "batting_team": "mw5jz3z05tswxa8m",
      "fielding_team": "ftxbf1wj156q30wd",
      "half": "top",
      "inning": 4,
      "kind": "runner_event",
      "narrative": "K. Willman advanced to second; L. Barry out at third p to 3b, caught stealing.",
      "runners": [
        {
          "cause": "advance",
          "from": 2,
          "out": false,
          "player_id": "kriqcbrfzfr25mz8",
          "scored": false,
          "to": 2
        },
        {
          "cause": "force_out",
          "from": 3,
          "out": true,
          "player_id": "ldy96obdqz56e59r",
          "scored": false,
          "to": 3
        }
      ],
      "scoring_play": false,
      "seq": 10
    },
    {
      "batting_team": "mw5jz3z05tswxa8m",
      "fielding_team": "ftxbf1wj156q30wd",
      "half": "top",
      "inning": 4,
      "kind": "inning_summary",
      "narrative": "Inning Summary: 0 Runs, 1 Hits, 0 Errors, 1 LOB",
      "scoring_play": false,
      "seq": 11,
      "summary": {
        "E": 0,
        "H": 1,
        "LOB": 1,
        "R": 0
      }
    },
    {
      "batting_team": "ftxbf1wj156q30wd",
      "fielding_team": "mw5jz3z05tswxa8m",
      "half": "bottom",
      "inning": 4,
      "kind": "inning_summary",
      "narrative": "Inning Summary: 3 Runs, 6 Hits, 0 Errors, 2 LOB",
      "scoring_play": false,
      "seq": 12,
      "summary": {
        "E": 0,
        "H": 6,
        "LOB": 2,
        "R": 3
      }
    },
    {
      "_derived": {
        "away_score_before": 0,
        "base_out_state": "000|0",
        "bases_after": [
          false,
          false,
          true
        ],
        "bases_before": [
          false,
          false,
          false
        ],
        "home_score_before": 0,
        "outs_after": 0,
        "outs_before": 0,
        "runs_on_play": 0
      },
      "batting_team": "mw5jz3z05tswxa8m",
      "fielding_team": "ftxbf1wj156q30wd",
      "half": "top",
      "inning": 5,
      "kind": "runner_event",
      "narrative": "C. Gordon advanced to third on a wild pitch.",
      "runners": [
        {
          "cause": "wild_pitch",
          "from": 3,
          "out": false,
          "player_id": "gj6w3ztw7zlm4y7g",
          "scored": false,
          "to": 3
        }
      ],
      "scoring_play": false,
      "seq": 13
    },
    {
      "batting_team": "mw5jz3z05tswxa8m",
      "fielding_team": "ftxbf1wj156q30wd",
      "half": "top",
      "inning": 5,
      "kind": "inning_summary",
      "narrative": "Inning Summary: 4 Runs, 3 Hits, 0 Errors, 2 LOB",
      "scoring_play": false,
      "seq": 14,
      "summary": {
        "E": 0,
        "H": 3,
        "LOB": 2,
        "R": 4
      }
    },
    {
      "batting_team": "ftxbf1wj156q30wd",
      "fielding_team": "mw5jz3z05tswxa8m",
      "half": "bottom",
      "inning": 5,
      "kind": "substitution",
      "narrative": "A. Sabouri to p for R. Fields.",
      "scoring_play": false,
      "seq": 15,
      "substitution": {
        "after_event_seq": 14,
        "kind": "pitching",
        "player_in": "256j63mgeotlic6q",
        "player_out": "y3vuu7pdahey0f27",
        "slot": null
      }
    },
    {
      "batting_team": "ftxbf1wj156q30wd",
      "fielding_team": "mw5jz3z05tswxa8m",
      "half": "bottom",
      "inning": 5,
      "kind": "inning_summary",
      "narrative": "Inning Summary: 1 Runs, 3 Hits, 0 Errors, 3 LOB",
      "scoring_play": false,
      "seq": 16,
      "summary": {
        "E": 0,
        "H": 3,
        "LOB": 3,
        "R": 1
      }
    },
    {
      "_derived": {
        "away_score_before": 0,
        "base_out_state": "000|0",
        "bases_after": [
          false,
          true,
          false
        ],
        "bases_before": [
          false,
          false,
          false
        ],
        "home_score_before": 0,
        "outs_after": 1,
        "outs_before": 0,
        "runs_on_play": 0
      },
      "batting_team": "mw5jz3z05tswxa8m",
      "fielding_team": "ftxbf1wj156q30wd",
      "half": "top",
      "inning": 6,
      "kind": "runner_event",
      "narrative": "C. Gordon out at first 2b to p; A. Fogel advanced to second.",
      "runners": [
        {
          "cause": "force_out",
          "from": 1,
          "out": true,
          "player_id": "gj6w3ztw7zlm4y7g",
          "scored": false,
          "to": 1
        },
        {
          "cause": "advance",
          "from": 2,
          "out": false,
          "player_id": "ov202no2zh1hpe7l",
          "scored": false,
          "to": 2
        }
      ],
      "scoring_play": false,
      "seq": 17
    },
    {
      "batting_team": "mw5jz3z05tswxa8m",
      "fielding_team": "ftxbf1wj156q30wd",
      "half": "top",
      "inning": 6,
      "kind": "inning_summary",
      "narrative": "Inning Summary: 1 Runs, 1 Hits, 0 Errors, 1 LOB",
      "scoring_play": false,
      "seq": 18,
      "summary": {
        "E": 0,
        "H": 1,
        "LOB": 1,
        "R": 1
      }
    },
    {
      "batting_team": "ftxbf1wj156q30wd",
      "fielding_team": "mw5jz3z05tswxa8m",
      "half": "bottom",
      "inning": 6,
      "kind": "inning_summary",
      "narrative": "Inning Summary: 0 Runs, 0 Hits, 0 Errors, 0 LOB",
      "scoring_play": false,
      "seq": 19,
      "summary": {
        "E": 0,
        "H": 0,
        "LOB": 0,
        "R": 0
      }
    },
    {
      "batting_team": "mw5jz3z05tswxa8m",
      "fielding_team": "ftxbf1wj156q30wd",
      "half": "top",
      "inning": 7,
      "kind": "substitution",
      "narrative": "R. Velazquez to p for Armstrong II.",
      "scoring_play": false,
      "seq": 20,
      "substitution": {
        "after_event_seq": 19,
        "kind": "pitching",
        "player_in": "2cmabhil7jgmm6c7",
        "player_out": "riant5z354rgz3ls",
        "slot": null
      }
    },
    {
      "batting_team": "mw5jz3z05tswxa8m",
      "fielding_team": "ftxbf1wj156q30wd",
      "half": "top",
      "inning": 7,
      "kind": "inning_summary",
      "narrative": "Inning Summary: 0 Runs, 0 Hits, 0 Errors, 0 LOB",
      "scoring_play": false,
      "seq": 21,
      "summary": {
        "E": 0,
        "H": 0,
        "LOB": 0,
        "R": 0
      }
    },
    {
      "batting_team": "ftxbf1wj156q30wd",
      "fielding_team": "mw5jz3z05tswxa8m",
      "half": "bottom",
      "inning": 7,
      "kind": "substitution",
      "narrative": "N. Bautista to p for A. Sabouri.",
      "scoring_play": false,
      "seq": 22,
      "substitution": {
        "after_event_seq": 21,
        "kind": "pitching",
        "player_in": "l598fosvptezoca1",
        "player_out": "256j63mgeotlic6q",
        "slot": null
      }
    },
    {
      "batting_team": "ftxbf1wj156q30wd",
      "fielding_team": "mw5jz3z05tswxa8m",
      "half": "bottom",
      "inning": 7,
      "kind": "inning_summary",
      "narrative": "Inning Summary: 2 Runs, 2 Hits, 0 Errors, 1 LOB",
      "scoring_play": false,
      "seq": 23,
      "summary": {
        "E": 0,
        "H": 2,
        "LOB": 1,
        "R": 2
      }
    },
    {
      "batting_team": "mw5jz3z05tswxa8m",
      "fielding_team": "ftxbf1wj156q30wd",
      "half": "top",
      "inning": 8,
      "kind": "inning_summary",
      "narrative": "Inning Summary: 2 Runs, 2 Hits, 0 Errors, 1 LOB",
      "scoring_play": false,
      "seq": 24,
      "summary": {
        "E": 0,
        "H": 2,
        "LOB": 1,
        "R": 2
      }
    },
    {
      "batting_team": "ftxbf1wj156q30wd",
      "fielding_team": "mw5jz3z05tswxa8m",
      "half": "bottom",
      "inning": 8,
      "kind": "substitution",
      "narrative": "N. Owen to p for A. Sabouri.",
      "scoring_play": false,
      "seq": 25,
      "substitution": {
        "after_event_seq": 24,
        "kind": "pitching",
        "player_in": "0og3efda00vmey7r",
        "player_out": "256j63mgeotlic6q",
        "slot": null
      }
    },
    {
      "batting_team": "ftxbf1wj156q30wd",
      "fielding_team": "mw5jz3z05tswxa8m",
      "half": "bottom",
      "inning": 8,
      "kind": "substitution",
      "narrative": "Z. Lampton to p for N. Owen.",
      "scoring_play": false,
      "seq": 26,
      "substitution": {
        "after_event_seq": 25,
        "kind": "pitching",
        "player_in": "3ntziz6um92c2z1f",
        "player_out": "0og3efda00vmey7r",
        "slot": null
      }
    },
    {
      "batting_team": "ftxbf1wj156q30wd",
      "fielding_team": "mw5jz3z05tswxa8m",
      "half": "bottom",
      "inning": 8,
      "kind": "inning_summary",
      "narrative": "Inning Summary: 0 Runs, 1 Hits, 1 Errors, 2 LOB",
      "scoring_play": false,
      "seq": 27,
      "summary": {
        "E": 1,
        "H": 1,
        "LOB": 2,
        "R": 0
      }
    },
    {
      "batting_team": "mw5jz3z05tswxa8m",
      "fielding_team": "ftxbf1wj156q30wd",
      "half": "top",
      "inning": 9,
      "kind": "substitution",
      "narrative": "A. Lopez to p for R. Velazquez.",
      "scoring_play": false,
      "seq": 28,
      "substitution": {
        "after_event_seq": 27,
        "kind": "pitching",
        "player_in": "1pk8u7yvk69kp4tb",
        "player_out": "2cmabhil7jgmm6c7",
        "slot": null
      }
    },
    {
      "batting_team": "mw5jz3z05tswxa8m",
      "fielding_team": "ftxbf1wj156q30wd",
      "half": "top",
      "inning": 9,
      "kind": "inning_summary",
      "narrative": "Inning Summary: 1 Runs, 1 Hits, 0 Errors, 1 LOB",
      "scoring_play": false,
      "seq": 29,
      "summary": {
        "E": 0,
        "H": 1,
        "LOB": 1,
        "R": 1
      }
    },
    {
      "batting_team": "ftxbf1wj156q30wd",
      "fielding_team": "mw5jz3z05tswxa8m",
      "half": "bottom",
      "inning": 9,
      "kind": "inning_summary",
      "narrative": "Inning Summary: 0 Runs, 0 Hits, 0 Errors, 0 LOB",
      "scoring_play": false,
      "seq": 30,
      "summary": {
        "E": 0,
        "H": 0,
        "LOB": 0,
        "R": 0
      }
    }
  ],
  "game_id": "20250817_7234",
  "linescore": {
    "innings": {
      "away": [
        4,
        2,
        3,
        0,
        4,
        1,
        0,
        2,
        1
      ],
      "home": [
        4,
        2,
        4,
        3,
        1,
        0,
        2,
        0,
        0
      ]
    },
    "totals": {
      "away": {
        "E": 4,
        "H": 18,
        "R": 17
      },
      "home": {
        "E": 1,
        "H": 24,
        "R": 16
      }
    }
  },
  "lineups": {
    "ftxbf1wj156q30wd": {
      "batting_order": [
        {
          "player_id": "2oyr5r7opv23s3pv",
          "slot": 1
        },
        {
          "player_id": "fed90noy2ji0f5sl",
          "slot": 2
        },
        {
          "player_id": "u2qlqon19x6c6w3h",
          "slot": 3
        },
        {
          "player_id": "al2kh9h54j8prr0q",
          "slot": 4
        },
        {
          "player_id": "3lh7rsmeoi2aw47t",
          "slot": 5
        },
        {
          "player_id": "hq3sxg95w4ouku79",
          "slot": 6
        },
        {
          "player_id": "yh45rm8iw5xetrej",
          "slot": 7
        },
        {
          "player_id": "q2ilr80howzzuw5j",
          "slot": 8
        },
        {
          "player_id": "b0wcwq9r4nvqldwt",
          "slot": 9
        }
      ],
      "substitutions": [
        {
          "after_event_seq": 19,
          "kind": "pitching",
          "player_in": "2cmabhil7jgmm6c7",
          "player_out": "riant5z354rgz3ls",
          "slot": null
        },
        {
          "after_event_seq": 27,
          "kind": "pitching",
          "player_in": "1pk8u7yvk69kp4tb",
          "player_out": "2cmabhil7jgmm6c7",
          "slot": null
        }
      ]
    },
    "mw5jz3z05tswxa8m": {
      "batting_order": [
        {
          "player_id": "zhwvtt83h5dg97d9",
          "slot": 1
        },
        {
          "player_id": "dys9nwsovxppppru",
          "slot": 2
        },
        {
          "player_id": "i2n256ipvurz082x",
          "slot": 3
        },
        {
          "player_id": "ov202no2zh1hpe7l",
          "slot": 4
        },
        {
          "player_id": "gj6w3ztw7zlm4y7g",
          "slot": 5
        },
        {
          "player_id": "ldy96obdqz56e59r",
          "slot": 6
        },
        {
          "player_id": "kriqcbrfzfr25mz8",
          "slot": 7
        },
        {
          "player_id": "uo4zsqqzhrhala5g",
          "slot": 8
        },
        {
          "player_id": "3vg4tjj6lny5kazm",
          "slot": 9
        }
      ],
      "substitutions": [
        {
          "after_event_seq": 3,
          "kind": "pitching",
          "player_in": "ye2uv5q9ocw9kc31",
          "player_out": "9oiv9xmbzm3nbrir",
          "slot": null
        },
        {
          "after_event_seq": 6,
          "kind": "pitching",
          "player_in": "y3vuu7pdahey0f27",
          "player_out": "ye2uv5q9ocw9kc31",
          "slot": null
        },
        {
          "after_event_seq": 14,
          "kind": "pitching",
          "player_in": "256j63mgeotlic6q",
          "player_out": "y3vuu7pdahey0f27",
          "slot": null
        },
        {
          "after_event_seq": 21,
          "kind": "pitching",
          "player_in": "l598fosvptezoca1",
          "player_out": "256j63mgeotlic6q",
          "slot": null
        },
        {
          "after_event_seq": 24,
          "kind": "pitching",
          "player_in": "0og3efda00vmey7r",
          "player_out": "256j63mgeotlic6q",
          "slot": null
        },
        {
          "after_event_seq": 25,
          "kind": "pitching",
          "player_in": "3ntziz6um92c2z1f",
          "player_out": "0og3efda00vmey7r",
          "slot": null
        }
      ]
    }
  },
  "meta": {
    "derived_replayer_version": "0.1.0",
    "fetched_at": "2026-07-12T17:32:16Z",
    "parse": {
      "events_count": 31,
      "replayable": false,
      "unparsed_count": 123,
      "warnings": [
        "[linescore] linescore: away inning 1 has no folded events but oracle expects 4",
        "[linescore] linescore: away inning 2 computed 0 != oracle 2",
        "[linescore] linescore: away inning 3 has no folded events but oracle expects 3",
        "[linescore] linescore: away inning 5 computed 0 != oracle 4",
        "[linescore] linescore: away inning 6 computed 0 != oracle 1",
        "[linescore] linescore: away inning 7 has no folded events but oracle expects 0",
        "[linescore] linescore: away inning 8 has no folded events but oracle expects 2",
        "[linescore] linescore: away inning 9 has no folded events but oracle expects 1",
        "[linescore] linescore: home inning 1 has no folded events but oracle expects 4",
        "[linescore] linescore: home inning 2 has no folded events but oracle expects 2",
        "[linescore] linescore: home inning 3 computed 0 != oracle 4",
        "[linescore] linescore: home inning 4 has no folded events but oracle expects 3",
        "[linescore] linescore: home inning 5 has no folded events but oracle expects 1",
        "[linescore] linescore: home inning 6 has no folded events but oracle expects 0",
        "[linescore] linescore: home inning 7 has no folded events but oracle expects 2",
        "[linescore] linescore: home inning 8 has no folded events but oracle expects 0",
        "[linescore] linescore: home inning 9 has no folded events but oracle expects 0",
        "[linescore] linescore: computed away final R 0 != oracle total 17",
        "[linescore] linescore: computed home final R 0 != oracle total 16",
        "[outs_per_half] outs_per_half: inning 2 top totals 1 outs (expected 3, no walk-off/unbatted exception applies)",
        "[outs_per_half] outs_per_half: inning 3 bottom totals 0 outs (expected 3, no walk-off/unbatted exception applies)",
        "[outs_per_half] outs_per_half: inning 4 top totals 1 outs (expected 3, no walk-off/unbatted exception applies)",
        "[outs_per_half] outs_per_half: inning 5 top totals 0 outs (expected 3, no walk-off/unbatted exception applies)",
        "[outs_per_half] outs_per_half: inning 6 top totals 1 outs (expected 3, no walk-off/unbatted exception applies)",
        "[lob] lob: inning 2 top folded LOB 0 != inning_summary LOB 2",
        "[lob] lob: inning 3 bottom folded LOB 1 != inning_summary LOB 2",
        "[lob] lob: inning 5 top folded LOB 1 != inning_summary LOB 2",
        "[illegal_transitions] illegal_transition: seq 2 runner gj6w3ztw7zlm4y7g advances from base 2 which was not occupied at event start",
        "[illegal_transitions] illegal_transition: seq 8 runner u2qlqon19x6c6w3h advances from base 3 which was not occupied at event start",
        "[illegal_transitions] illegal_transition: seq 10 runner kriqcbrfzfr25mz8 advances from base 2 which was not occupied at event start",
        "[illegal_transitions] illegal_transition: seq 10 runner ldy96obdqz56e59r advances from base 3 which was not occupied at event start",
        "[illegal_transitions] illegal_transition: seq 13 runner gj6w3ztw7zlm4y7g advances from base 3 which was not occupied at event start",
        "[illegal_transitions] illegal_transition: seq 17 runner gj6w3ztw7zlm4y7g advances from base 1 which was not occupied at event start",
        "[illegal_transitions] illegal_transition: seq 17 runner ov202no2zh1hpe7l advances from base 2 which was not occupied at event start"
      ]
    },
    "parsed_at": "2026-07-12T17:40:31Z",
    "parser_version": "0.1.0",
    "source_sha256": "8ab71353a8e8f7b5396382c7affc7b9ca097beffcddbf6e6143c244e7feda4d7",
    "source_url": "https://www.pioneerleague.com/sports/bsb/2025/boxscores/20250817_7234.xml"
  },
  "players": {
    "0og3efda00vmey7r": {
      "bats_side": null,
      "last_name": "Owen",
      "name": "Noah Owen",
      "player_id": "0og3efda00vmey7r",
      "positions": [
        "p"
      ],
      "team_id": "mw5jz3z05tswxa8m"
    },
    "1pk8u7yvk69kp4tb": {
      "bats_side": null,
      "last_name": "Lopez",
      "name": "Alain Lopez",
      "player_id": "1pk8u7yvk69kp4tb",
      "positions": [
        "p"
      ],
      "team_id": "ftxbf1wj156q30wd"
    },
    "256j63mgeotlic6q": {
      "bats_side": null,
      "last_name": "Sabouri",
      "name": "Arman Sabouri",
      "player_id": "256j63mgeotlic6q",
      "positions": [
        "p"
      ],
      "team_id": "mw5jz3z05tswxa8m"
    },
    "2cmabhil7jgmm6c7": {
      "bats_side": null,
      "last_name": "Velazquez",
      "name": "Ryan Velazquez",
      "player_id": "2cmabhil7jgmm6c7",
      "positions": [
        "p"
      ],
      "team_id": "ftxbf1wj156q30wd"
    },
    "2oyr5r7opv23s3pv": {
      "bats_side": null,
      "last_name": "Roberts",
      "name": "Brett Roberts",
      "player_id": "2oyr5r7opv23s3pv",
      "positions": [
        "cf"
      ],
      "team_id": "ftxbf1wj156q30wd"
    },
    "3lh7rsmeoi2aw47t": {
      "bats_side": null,
      "last_name": "Landis",
      "name": "Quintt Landis",
      "player_id": "3lh7rsmeoi2aw47t",
      "positions": [
        "dh/lf"
      ],
      "team_id": "ftxbf1wj156q30wd"
    },
    "3ntziz6um92c2z1f": {
      "bats_side": null,
      "last_name": "Lampton",
      "name": "Zac Lampton",
      "player_id": "3ntziz6um92c2z1f",
      "positions": [
        "p"
      ],
      "team_id": "mw5jz3z05tswxa8m"
    },
    "3vg4tjj6lny5kazm": {
      "bats_side": null,
      "last_name": "Smith",
      "name": "Taylor Smith",
      "player_id": "3vg4tjj6lny5kazm",
      "positions": [
        "1b"
      ],
      "team_id": "mw5jz3z05tswxa8m"
    },
    "7hawkykz292el0ws": {
      "bats_side": null,
      "last_name": "Perez",
      "name": "Carlos Perez",
      "player_id": "7hawkykz292el0ws",
      "positions": [
        "3b"
      ],
      "team_id": "mw5jz3z05tswxa8m"
    },
    "9oiv9xmbzm3nbrir": {
      "bats_side": null,
      "last_name": "Day",
      "name": "Dawson Day",
      "player_id": "9oiv9xmbzm3nbrir",
      "positions": [
        "p"
      ],
      "team_id": "mw5jz3z05tswxa8m"
    },
    "al2kh9h54j8prr0q": {
      "bats_side": null,
      "last_name": "Johnson",
      "name": "Justin Johnson",
      "player_id": "al2kh9h54j8prr0q",
      "positions": [
        "1b/dh"
      ],
      "team_id": "ftxbf1wj156q30wd"
    },
    "b0wcwq9r4nvqldwt": {
      "bats_side": null,
      "last_name": "Fabian",
      "name": "Matt Fabian",
      "player_id": "b0wcwq9r4nvqldwt",
      "positions": [
        "lf/1b"
      ],
      "team_id": "ftxbf1wj156q30wd"
    },
    "dys9nwsovxppppru": {
      "bats_side": null,
      "last_name": "Rosario",
      "name": "Mike Rosario",
      "player_id": "dys9nwsovxppppru",
      "positions": [
        "rf"
      ],
      "team_id": "mw5jz3z05tswxa8m"
    },
    "fed90noy2ji0f5sl": {
      "bats_side": null,
      "last_name": "Denton",
      "name": "Zane Denton",
      "player_id": "fed90noy2ji0f5sl",
      "positions": [
        "3b"
      ],
      "team_id": "ftxbf1wj156q30wd"
    },
    "gj6w3ztw7zlm4y7g": {
      "bats_side": null,
      "last_name": "Gordon",
      "name": "Colin Gordon",
      "player_id": "gj6w3ztw7zlm4y7g",
      "positions": [
        "dh"
      ],
      "team_id": "mw5jz3z05tswxa8m"
    },
    "hq3sxg95w4ouku79": {
      "bats_side": null,
      "last_name": "McKenzie",
      "name": "T.J. McKenzie",
      "player_id": "hq3sxg95w4ouku79",
      "positions": [
        "rf"
      ],
      "team_id": "ftxbf1wj156q30wd"
    },
    "i2n256ipvurz082x": {
      "bats_side": null,
      "last_name": "Klemp",
      "name": "Nich Klemp",
      "player_id": "i2n256ipvurz082x",
      "positions": [
        "c"
      ],
      "team_id": "mw5jz3z05tswxa8m"
    },
    "khcrwbcbipu2bcmg": {
      "bats_side": null,
      "last_name": "Cunningham",
      "name": "Tahj Cunningham",
      "player_id": "khcrwbcbipu2bcmg",
      "positions": [
        "p"
      ],
      "team_id": "ftxbf1wj156q30wd"
    },
    "kriqcbrfzfr25mz8": {
      "bats_side": null,
      "last_name": "Willman",
      "name": "Kamron Willman",
      "player_id": "kriqcbrfzfr25mz8",
      "positions": [
        "ss"
      ],
      "team_id": "mw5jz3z05tswxa8m"
    },
    "l598fosvptezoca1": {
      "bats_side": null,
      "last_name": "Bautista",
      "name": "Nick Bautista",
      "player_id": "l598fosvptezoca1",
      "positions": [
        "p"
      ],
      "team_id": "mw5jz3z05tswxa8m"
    },
    "larymvbb4jx0h5i5": {
      "bats_side": null,
      "last_name": "Pena",
      "name": "Roberto Pena",
      "player_id": "larymvbb4jx0h5i5",
      "positions": [
        "1b"
      ],
      "team_id": "mw5jz3z05tswxa8m"
    },
    "ldy96obdqz56e59r": {
      "bats_side": null,
      "last_name": "Barry",
      "name": "Leyton Barry",
      "player_id": "ldy96obdqz56e59r",
      "positions": [
        "cf"
      ],
      "team_id": "mw5jz3z05tswxa8m"
    },
    "ov202no2zh1hpe7l": {
      "bats_side": null,
      "last_name": "Fogel",
      "name": "Adam Fogel",
      "player_id": "ov202no2zh1hpe7l",
      "positions": [
        "lf"
      ],
      "team_id": "mw5jz3z05tswxa8m"
    },
    "pc4t8yra3oyd3bcw": {
      "bats_side": null,
      "last_name": "Alonso",
      "name": "Andres Alonso",
      "player_id": "pc4t8yra3oyd3bcw",
      "positions": [
        "p"
      ],
      "team_id": "ftxbf1wj156q30wd"
    },
    "q2ilr80howzzuw5j": {
      "bats_side": null,
      "last_name": "Martinez",
      "name": "Marco Martinez",
      "player_id": "q2ilr80howzzuw5j",
      "positions": [
        "pr"
      ],
      "team_id": "ftxbf1wj156q30wd"
    },
    "riant5z354rgz3ls": {
      "bats_side": null,
      "last_name": "Armstrong",
      "name": "Eldridge Armstrong III",
      "player_id": "riant5z354rgz3ls",
      "positions": [
        "p"
      ],
      "team_id": "ftxbf1wj156q30wd"
    },
    "u2qlqon19x6c6w3h": {
      "bats_side": null,
      "last_name": "Moody",
      "name": "Kai Moody",
      "player_id": "u2qlqon19x6c6w3h",
      "positions": [
        "2b"
      ],
      "team_id": "ftxbf1wj156q30wd"
    },
    "uo4zsqqzhrhala5g": {
      "bats_side": null,
      "last_name": "Piatkiewicz",
      "name": "Jeremy Piatkiewicz",
      "player_id": "uo4zsqqzhrhala5g",
      "positions": [
        "ss"
      ],
      "team_id": "mw5jz3z05tswxa8m"
    },
    "wclemxwmo2sy8wth": {
      "bats_side": null,
      "last_name": "Pagani",
      "name": "Edwin Martinez Pagani",
      "player_id": "wclemxwmo2sy8wth",
      "positions": [
        "ss"
      ],
      "team_id": "ftxbf1wj156q30wd"
    },
    "y3vuu7pdahey0f27": {
      "bats_side": null,
      "last_name": "Fields",
      "name": "Reece Fields",
      "player_id": "y3vuu7pdahey0f27",
      "positions": [
        "p"
      ],
      "team_id": "mw5jz3z05tswxa8m"
    },
    "ye2uv5q9ocw9kc31": {
      "bats_side": null,
      "last_name": "Armstrong",
      "name": "Andrew Armstrong",
      "player_id": "ye2uv5q9ocw9kc31",
      "positions": [
        "p"
      ],
      "team_id": "mw5jz3z05tswxa8m"
    },
    "yh45rm8iw5xetrej": {
      "bats_side": null,
      "last_name": "Veloz",
      "name": "Omar Veloz",
      "player_id": "yh45rm8iw5xetrej",
      "positions": [
        "c"
      ],
      "team_id": "ftxbf1wj156q30wd"
    },
    "zhwvtt83h5dg97d9": {
      "bats_side": null,
      "last_name": "Wilkerson",
      "name": "Colby Wilkerson",
      "player_id": "zhwvtt83h5dg97d9",
      "positions": [
        "2b"
      ],
      "team_id": "mw5jz3z05tswxa8m"
    }
  },
  "schema_version": "1.1.0",
  "season": 2025,
  "source": {
    "league_id": "pioneer",
    "provider": "prestosports",
    "site": "www.pioneerleague.com"
  },
  "status": "final",
  "teams": {
    "away": {
      "name": "Missoula PaddleHeads",
      "team_id": "mw5jz3z05tswxa8m"
    },
    "home": {
      "name": "Colorado Springs Sky Sox",
      "team_id": "ftxbf1wj156q30wd"
    }
  },
  "unparsed": [
    {
      "location": {
        "half": "top",
        "inning": 1,
        "line_index": 0
      },
      "raw": "M. Fabian to 1b.",
      "reason": "no count-tail on primary clause, and clause did not match any runner rule either: 'M. Fabian to 1b'"
    },
    {
      "location": {
        "half": "top",
        "inning": 1,
        "line_index": 1
      },
      "raw": "Q. Landis to lf.",
      "reason": "no count-tail on primary clause, and clause did not match any runner rule either: 'Q. Landis to lf'"
    },
    {
      "location": {
        "half": "top",
        "inning": 1,
        "line_index": 2
      },
      "raw": "J. Johnson to dh.",
      "reason": "no count-tail on primary clause, and clause did not match any runner rule either: 'J. Johnson to dh'"
    },
    {
      "location": {
        "half": "top",
        "inning": 1,
        "line_index": 3
      },
      "raw": "C. Wilkerson singled to shortstop.",
      "reason": "no count-tail on primary clause, and clause did not match any runner rule either: 'C. Wilkerson singled to shortstop'"
    },
    {
      "location": {
        "half": "top",
        "inning": 1,
        "line_index": 4
      },
      "raw": "M. Rosario singled to right field; C. Wilkerson advanced to second.",
      "reason": "no count-tail on primary clause, and clause did not match any runner rule either: 'M. Rosario singled to right field'"
    },
    {
      "location": {
        "half": "top",
        "inning": 1,
        "line_index": 5
      },
      "raw": "N. Klemp homered to right field, 3 RBI; M. Rosario scored; C. Wilkerson scored.",
      "reason": "no count-tail on primary clause, and clause did not match any runner rule either: 'N. Klemp homered to right field, 3 RBI'"
    },
    {
      "location": {
        "half": "top",
        "inning": 1,
        "line_index": 6
      },
      "raw": "A. Fogel grounded out to ss.\n                                                                                                                                \t\t\t\t\t(1 out)",
      "reason": "no count-tail on primary clause, and clause did not match any runner rule either: 'A. Fogel grounded out to ss'"
    },
    {
      "location": {
        "half": "top",
        "inning": 1,
        "line_index": 7
      },
      "raw": "C. Gordon struck out swinging, out at first c to 1b.\n                                                                                                                                \t\t\t\t\t(2 out)",
      "reason": "runner clause name did not resolve uniquely"
    },
    {
      "location": {
        "half": "top",
        "inning": 1,
        "line_index": 8
      },
      "raw": "L. Barry homered to center field, RBI.",
      "reason": "no count-tail on primary clause, and clause did not match any runner rule either: 'L. Barry homered to center field, RBI'"
    },
    {
      "location": {
        "half": "top",
        "inning": 1,
        "line_index": 9
      },
      "raw": "K. Willman walked.",
      "reason": "no count-tail on primary clause, and clause did not match any runner rule either: 'K. Willman walked'"
    },
    {
      "location": {
        "half": "top",
        "inning": 1,
        "line_index": 10
      },
      "raw": "T. Smith walked; K. Willman advanced to second.",
      "reason": "no count-tail on primary clause, and clause did not match any runner rule either: 'T. Smith walked'"
    },
    {
      "location": {
        "half": "top",
        "inning": 1,
        "line_index": 11
      },
      "raw": "C. Perez popped out to p.\n                                                                                                                                \t\t\t\t\t(3 out)",
      "reason": "no count-tail on primary clause, and clause did not match any runner rule either: 'C. Perez popped out to p'"
    },
    {
      "location": {
        "half": "bottom",
        "inning": 1,
        "line_index": 0
      },
      "raw": "B. Robert singled to right field.",
      "reason": "no count-tail on primary clause, and clause did not match any runner rule either: 'B. Robert singled to right field'"
    },
    {
      "location": {
        "half": "bottom",
        "inning": 1,
        "line_index": 1
      },
      "raw": "B. Robert out at second c to 2b, caught stealing.\n                                                                                                                                                                                        \t\t\t\t\t(1 out)",
      "reason": "runner clause name did not resolve uniquely"
    },
    {
      "location": {
        "half": "bottom",
        "inning": 1,
        "line_index": 2
      },
      "raw": "Z. Denton doubled to left field.",
      "reason": "no count-tail on primary clause, and clause did not match any runner rule either: 'Z. Denton doubled to left field'"
    },
    {
      "location": {
        "half": "bottom",
        "inning": 1,
        "line_index": 3
      },
      "raw": "K. Moody doubled down the lf line, RBI; Z. Denton scored.",
      "reason": "no count-tail on primary clause, and clause did not match any runner rule either: 'K. Moody doubled down the lf line, RBI'"
    },
    {
      "location": {
        "half": "bottom",
        "inning": 1,
        "line_index": 4
      },
      "raw": "J. Johnson struck out swinging.\n                                                                                                                                \t\t\t\t\t(2 out)",
      "reason": "no count-tail on primary clause, and clause did not match any runner rule either: 'J. Johnson struck out swinging'"
    },
    {
      "location": {
        "half": "bottom",
        "inning": 1,
        "line_index": 5
      },
      "raw": "Q. Landis walked.",
      "reason": "no count-tail on primary clause, and clause did not match any runner rule either: 'Q. Landis walked'"
    },
    {
      "location": {
        "half": "bottom",
        "inning": 1,
        "line_index": 6
      },
      "raw": "T. McKenzie singled to center field, RBI; Q. Landis advanced to third; K. Moody scored.",
      "reason": "no count-tail on primary clause, and clause did not match any runner rule either: 'T. McKenzie singled to center field, RBI'"
    },
    {
      "location": {
        "half": "bottom",
        "inning": 1,
        "line_index": 7
      },
      "raw": "O. Veloz singled to center field, advanced to second on the throw, 2 RBI; T. McKenzie scored; Q. Landis scored.",
      "reason": "no count-tail on primary clause, and clause did not match any runner rule either: 'O. Veloz singled to center field, advanced to second on the throw, 2 RBI'"
    },
    {
      "location": {
        "half": "bottom",
        "inning": 1,
        "line_index": 8
      },
      "raw": "M. Fabian struck out looking.\n                                                                                                                                \t\t\t\t\t(3 out)",
      "reason": "no count-tail on primary clause, and clause did not match any runner rule either: 'M. Fabian struck out looking'"
    },
    {
      "location": {
        "half": "top",
        "inning": 2,
        "line_index": 0
      },
      "raw": "C. Wilkerson singled to shortstop.",
      "reason": "no count-tail on primary clause, and clause did not match any runner rule either: 'C. Wilkerson singled to shortstop'"
    },
    {
      "location": {
        "half": "top",
        "inning": 2,
        "line_index": 1
      },
      "raw": "M. Rosario popped up to 2b.\n                                                                                                                                \t\t\t\t\t(1 out)",
      "reason": "no count-tail on primary clause, and clause did not match any runner rule either: 'M. Rosario popped up to 2b'"
    },
    {
      "location": {
        "half": "top",
        "inning": 2,
        "line_index": 2
      },
      "raw": "N. Klemp flied out to cf.\n                                                                                                                                \t\t\t\t\t(2 out)",
      "reason": "no count-tail on primary clause, and clause did not match any runner rule either: 'N. Klemp flied out to cf'"
    },
    {
      "location": {
        "half": "top",
        "inning": 2,
        "line_index": 3
      },
      "raw": "A. Fogel homered to left center, 2 RBI; C. Wilkerson scored.",
      "reason": "no count-tail on primary clause, and clause did not match any runner rule either: 'A. Fogel homered to left center, 2 RBI'"
    },
    {
      "location": {
        "half": "top",
        "inning": 2,
        "line_index": 4
      },
      "raw": "C. Gordon singled to left field.",
      "reason": "no count-tail on primary clause, and clause did not match any runner rule either: 'C. Gordon singled to left field'"
    },
    {
      "location": {
        "half": "top",
        "inning": 2,
        "line_index": 5
      },
      "raw": "L. Barry walked; C. Gordon advanced to second.",
      "reason": "no count-tail on primary clause, and clause did not match any runner rule either: 'L. Barry walked'"
    },
    {
      "location": {
        "half": "bottom",
        "inning": 2,
        "line_index": 0
      },
      "raw": "E. Pagani doubled to left center.",
      "reason": "no count-tail on primary clause, and clause did not match any runner rule either: 'E. Pagani doubled to left center'"
    },
    {
      "location": {
        "half": "bottom",
        "inning": 2,
        "line_index": 1
      },
      "raw": "B. Robert homered to left center, 2 RBI; E. Pagani scored.",
      "reason": "no count-tail on primary clause, and clause did not match any runner rule either: 'B. Robert homered to left center, 2 RBI'"
    },
    {
      "location": {
        "half": "bottom",
        "inning": 2,
        "line_index": 2
      },
      "raw": "Z. Denton singled to center field.",
      "reason": "no count-tail on primary clause, and clause did not match any runner rule either: 'Z. Denton singled to center field'"
    },
    {
      "location": {
        "half": "bottom",
        "inning": 2,
        "line_index": 3
      },
      "raw": "K. Moody walked; Z. Denton advanced to second.",
      "reason": "no count-tail on primary clause, and clause did not match any runner rule either: 'K. Moody walked'"
    },
    {
      "location": {
        "half": "bottom",
        "inning": 2,
        "line_index": 5
      },
      "raw": "J. Johnson flied out to rf.\n                                                                                                                                \t\t\t\t\t(1 out)",
      "reason": "no count-tail on primary clause, and clause did not match any runner rule either: 'J. Johnson flied out to rf'"
    },
    {
      "location": {
        "half": "bottom",
        "inning": 2,
        "line_index": 6
      },
      "raw": "Q. Landis popped out to 1b.\n                                                                                                                                \t\t\t\t\t(2 out)",
      "reason": "no count-tail on primary clause, and clause did not match any runner rule either: 'Q. Landis popped out to 1b'"
    },
    {
      "location": {
        "half": "bottom",
        "inning": 2,
        "line_index": 7
      },
      "raw": "T. McKenzie reached on a fielder's choice; K. Moody out at second 3b to 2b.\n                                                                                                                                                                                        \t\t\t\t\t(3 out)",
      "reason": "no count-tail on primary clause, and clause did not match any runner rule either: \"T. McKenzie reached on a fielder's choice\""
    },
    {
      "location": {
        "half": "top",
        "inning": 3,
        "line_index": 0
      },
      "raw": "K. Willman homered to center field, RBI.",
      "reason": "no count-tail on primary clause, and clause did not match any runner rule either: 'K. Willman homered to center field, RBI'"
    },
    {
      "location": {
        "half": "top",
        "inning": 3,
        "line_index": 1
      },
      "raw": "T. Smith grounded out to 3b.\n                                                                                                                                \t\t\t\t\t(1 out)",
      "reason": "no count-tail on primary clause, and clause did not match any runner rule either: 'T. Smith grounded out to 3b'"
    },
    {
      "location": {
        "half": "top",
        "inning": 3,
        "line_index": 2
      },
      "raw": "C. Perez singled to center field.",
      "reason": "no count-tail on primary clause, and clause did not match any runner rule either: 'C. Perez singled to center field'"
    },
    {
      "location": {
        "half": "top",
        "inning": 3,
        "line_index": 3
      },
      "raw": "C. Wilkerson flied out to rf.\n                                                                                                                                \t\t\t\t\t(2 out)",
      "reason": "no count-tail on primary clause, and clause did not match any runner rule either: 'C. Wilkerson flied out to rf'"
    },
    {
      "location": {
        "half": "top",
        "inning": 3,
        "line_index": 4
      },
      "raw": "M. Rosario singled to center field; C. Perez advanced to second.",
      "reason": "no count-tail on primary clause, and clause did not match any runner rule either: 'M. Rosario singled to center field'"
    },
    {
      "location": {
        "half": "top",
        "inning": 3,
        "line_index": 5
      },
      "raw": "N. Klemp walked; M. Rosario advanced to second; C. Perez advanced to third.",
      "reason": "no count-tail on primary clause, and clause did not match any runner rule either: 'N. Klemp walked'"
    },
    {
      "location": {
        "half": "top",
        "inning": 3,
        "line_index": 6
      },
      "raw": "A. Fogel reached first on an error by 1b; N. Klemp advanced to third; M. Rosario scored, unearned; C. Perez scored, unearned.",
      "reason": "no count-tail on primary clause, and clause did not match any runner rule either: 'A. Fogel reached first on an error by 1b'"
    },
    {
      "location": {
        "half": "top",
        "inning": 3,
        "line_index": 7
      },
      "raw": "C. Gordon flied out to lf.\n                                                                                                                                \t\t\t\t\t(3 out)",
      "reason": "no count-tail on primary clause, and clause did not match any runner rule either: 'C. Gordon flied out to lf'"
    },
    {
      "location": {
        "half": "bottom",
        "inning": 3,
        "line_index": 0
      },
      "raw": "O. Veloz flied out to rf.\n                                                                                                                                \t\t\t\t\t(1 out)",
      "reason": "no count-tail on primary clause, and clause did not match any runner rule either: 'O. Veloz flied out to rf'"
    },
    {
      "location": {
        "half": "bottom",
        "inning": 3,
        "line_index": 1
      },
      "raw": "M. Fabian hit by pitch.",
      "reason": "no count-tail on primary clause, and clause did not match any runner rule either: 'M. Fabian hit by pitch'"
    },
    {
      "location": {
        "half": "bottom",
        "inning": 3,
        "line_index": 2
      },
      "raw": "E. Pagani struck out looking.\n                                                                                                                                \t\t\t\t\t(2 out)",
      "reason": "no count-tail on primary clause, and clause did not match any runner rule either: 'E. Pagani struck out looking'"
    },
    {
      "location": {
        "half": "bottom",
        "inning": 3,
        "line_index": 3
      },
      "raw": "B. Robert walked; M. Fabian advanced to second.",
      "reason": "no count-tail on primary clause, and clause did not match any runner rule either: 'B. Robert walked'"
    },
    {
      "location": {
        "half": "bottom",
        "inning": 3,
        "line_index": 4
      },
      "raw": "Z. Denton homered down the lf line, 3 RBI; B. Robert scored; M. Fabian scored.",
      "reason": "no count-tail on primary clause, and clause did not match any runner rule either: 'Z. Denton homered down the lf line, 3 RBI'"
    },
    {
      "location": {
        "half": "bottom",
        "inning": 3,
        "line_index": 6
      },
      "raw": "K. Moody doubled to right field.",
      "reason": "no count-tail on primary clause, and clause did not match any runner rule either: 'K. Moody doubled to right field'"
    },
    {
      "location": {
        "half": "bottom",
        "inning": 3,
        "line_index": 8
      },
      "raw": "J. Johnson doubled down the rf line, RBI; K. Moody scored.",
      "reason": "no count-tail on primary clause, and clause did not match any runner rule either: 'J. Johnson doubled down the rf line, RBI'"
    },
    {
      "location": {
        "half": "bottom",
        "inning": 3,
        "line_index": 9
      },
      "raw": "Q. Landis singled to left field; J. Johnson advanced to third.",
      "reason": "no count-tail on primary clause, and clause did not match any runner rule either: 'Q. Landis singled to left field'"
    },
    {
      "location": {
        "half": "bottom",
        "inning": 3,
        "line_index": 10
      },
      "raw": "T. McKenzie reached on a fielder's choice; Q. Landis out at second ss to 2b.\n                                                                                                                                                                                        \t\t\t\t\t(3 out)",
      "reason": "no count-tail on primary clause, and clause did not match any runner rule either: \"T. McKenzie reached on a fielder's choice\""
    },
    {
      "location": {
        "half": "top",
        "inning": 4,
        "line_index": 0
      },
      "raw": "L. Barry doubled down the rf line.",
      "reason": "no count-tail on primary clause, and clause did not match any runner rule either: 'L. Barry doubled down the rf line'"
    },
    {
      "location": {
        "half": "top",
        "inning": 4,
        "line_index": 1
      },
      "raw": "K. Willman walked.",
      "reason": "no count-tail on primary clause, and clause did not match any runner rule either: 'K. Willman walked'"
    },
    {
      "location": {
        "half": "top",
        "inning": 4,
        "line_index": 3
      },
      "raw": "T. Smith grounded out to 3b.\n                                                                                                                                \t\t\t\t\t(2 out)",
      "reason": "no count-tail on primary clause, and clause did not match any runner rule either: 'T. Smith grounded out to 3b'"
    },
    {
      "location": {
        "half": "top",
        "inning": 4,
        "line_index": 4
      },
      "raw": "C. Perez grounded out to 2b.\n                                                                                                                                \t\t\t\t\t(3 out)",
      "reason": "no count-tail on primary clause, and clause did not match any runner rule either: 'C. Perez grounded out to 2b'"
    },
    {
      "location": {
        "half": "bottom",
        "inning": 4,
        "line_index": 0
      },
      "raw": "O. Veloz doubled to right center.",
      "reason": "no count-tail on primary clause, and clause did not match any runner rule either: 'O. Veloz doubled to right center'"
    },
    {
      "location": {
        "half": "bottom",
        "inning": 4,
        "line_index": 1
      },
      "raw": "M. Fabian singled to right center, out at second rf to c to ss, RBI; O. Veloz scored.",
      "reason": "runner clause name did not resolve uniquely"
    },
    {
      "location": {
        "half": "bottom",
        "inning": 4,
        "line_index": 2
      },
      "raw": "E. Pagani singled to center field.",
      "reason": "no count-tail on primary clause, and clause did not match any runner rule either: 'E. Pagani singled to center field'"
    },
    {
      "location": {
        "half": "bottom",
        "inning": 4,
        "line_index": 3
      },
      "raw": "B. Robert singled, advanced to third on an error by cf, scored on an error by c, unearned; E. Pagani scored.",
      "reason": "runner clause name did not resolve uniquely"
    },
    {
      "location": {
        "half": "bottom",
        "inning": 4,
        "line_index": 4
      },
      "raw": "Z. Denton singled to right field.",
      "reason": "no count-tail on primary clause, and clause did not match any runner rule either: 'Z. Denton singled to right field'"
    },
    {
      "location": {
        "half": "bottom",
        "inning": 4,
        "line_index": 5
      },
      "raw": "K. Moody singled to left center; Z. Denton advanced to second.",
      "reason": "no count-tail on primary clause, and clause did not match any runner rule either: 'K. Moody singled to left center'"
    },
    {
      "location": {
        "half": "bottom",
        "inning": 4,
        "line_index": 6
      },
      "raw": "J. Johnson flied out to cf; Z. Denton advanced to third.\n                                                                                                                                                                                    \t\t\t\t\t(2 out)",
      "reason": "no count-tail on primary clause, and clause did not match any runner rule either: 'J. Johnson flied out to cf'"
    },
    {
      "location": {
        "half": "bottom",
        "inning": 4,
        "line_index": 7
      },
      "raw": "Q. Landis flied out to rf.\n                                                                                                                                \t\t\t\t\t(3 out)",
      "reason": "no count-tail on primary clause, and clause did not match any runner rule either: 'Q. Landis flied out to rf'"
    },
    {
      "location": {
        "half": "top",
        "inning": 5,
        "line_index": 0
      },
      "raw": "T. Cunningha to p for A. Alonso.",
      "reason": "substitution names did not resolve uniquely on the fielding side: out='A. Alonso' in='T. Cunningha'"
    },
    {
      "location": {
        "half": "top",
        "inning": 5,
        "line_index": 1
      },
      "raw": "C. Wilkerson walked.",
      "reason": "no count-tail on primary clause, and clause did not match any runner rule either: 'C. Wilkerson walked'"
    },
    {
      "location": {
        "half": "top",
        "inning": 5,
        "line_index": 2
      },
      "raw": "M. Rosario hit by pitch; C. Wilkerson advanced to second.",
      "reason": "no count-tail on primary clause, and clause did not match any runner rule either: 'M. Rosario hit by pitch'"
    },
    {
      "location": {
        "half": "top",
        "inning": 5,
        "line_index": 3
      },
      "raw": "N. Klemp homered to right field, 3 RBI; M. Rosario scored; C. Wilkerson scored.",
      "reason": "no count-tail on primary clause, and clause did not match any runner rule either: 'N. Klemp homered to right field, 3 RBI'"
    },
    {
      "location": {
        "half": "top",
        "inning": 5,
        "line_index": 4
      },
      "raw": "A. Fogel flied out to rf.\n                                                                                                                                \t\t\t\t\t(1 out)",
      "reason": "no count-tail on primary clause, and clause did not match any runner rule either: 'A. Fogel flied out to rf'"
    },
    {
      "location": {
        "half": "top",
        "inning": 5,
        "line_index": 5
      },
      "raw": "C. Gordon walked.",
      "reason": "no count-tail on primary clause, and clause did not match any runner rule either: 'C. Gordon walked'"
    },
    {
      "location": {
        "half": "top",
        "inning": 5,
        "line_index": 6
      },
      "raw": "L. Barry struck out swinging; C. Gordon advanced to second on a wild pitch.\n                                                                                                                                                                                    \t\t\t\t\t(2 out)",
      "reason": "no count-tail on primary clause, and clause did not match any runner rule either: 'L. Barry struck out swinging'"
    },
    {
      "location": {
        "half": "top",
        "inning": 5,
        "line_index": 7
      },
      "raw": "J. Piatkiewi pinch hit for K. Willman.",
      "reason": "no count-tail on primary clause, and clause did not match any runner rule either: 'J. Piatkiewi pinch hit for K. Willman'"
    },
    {
      "location": {
        "half": "top",
        "inning": 5,
        "line_index": 9
      },
      "raw": "J. Piatkiewi singled to center field, RBI; C. Gordon scored.",
      "reason": "no count-tail on primary clause, and clause did not match any runner rule either: 'J. Piatkiewi singled to center field, RBI'"
    },
    {
      "location": {
        "half": "top",
        "inning": 5,
        "line_index": 10
      },
      "raw": "T. Smith singled to third base; J. Piatkiewi advanced to third.",
      "reason": "no count-tail on primary clause, and clause did not match any runner rule either: 'T. Smith singled to third base'"
    },
    {
      "location": {
        "half": "top",
        "inning": 5,
        "line_index": 11
      },
      "raw": "C. Perez flied out to lf.\n                                                                                                                                \t\t\t\t\t(3 out)",
      "reason": "no count-tail on primary clause, and clause did not match any runner rule either: 'C. Perez flied out to lf'"
    },
    {
      "location": {
        "half": "bottom",
        "inning": 5,
        "line_index": 0
      },
      "raw": "J. Piatkiewi to ss.",
      "reason": "no count-tail on primary clause, and clause did not match any runner rule either: 'J. Piatkiewi to ss'"
    },
    {
      "location": {
        "half": "bottom",
        "inning": 5,
        "line_index": 2
      },
      "raw": "T. McKenzie walked.",
      "reason": "no count-tail on primary clause, and clause did not match any runner rule either: 'T. McKenzie walked'"
    },
    {
      "location": {
        "half": "bottom",
        "inning": 5,
        "line_index": 3
      },
      "raw": "O. Veloz singled to center field; T. McKenzie advanced to third.",
      "reason": "no count-tail on primary clause, and clause did not match any runner rule either: 'O. Veloz singled to center field'"
    },
    {
      "location": {
        "half": "bottom",
        "inning": 5,
        "line_index": 4
      },
      "raw": "M. Fabian reached on a fielder's choice, RBI; O. Veloz out at second ss to 2b; T. McKenzie scored.",
      "reason": "no count-tail on primary clause, and clause did not match any runner rule either: \"M. Fabian reached on a fielder's choice, RBI\""
    },
    {
      "location": {
        "half": "bottom",
        "inning": 5,
        "line_index": 5
      },
      "raw": "E. Pagani singled to pitcher; M. Fabian advanced to second.",
      "reason": "no count-tail on primary clause, and clause did not match any runner rule either: 'E. Pagani singled to pitcher'"
    },
    {
      "location": {
        "half": "bottom",
        "inning": 5,
        "line_index": 6
      },
      "raw": "B. Robert singled to right field; E. Pagani advanced to second; M. Fabian advanced to third.",
      "reason": "no count-tail on primary clause, and clause did not match any runner rule either: 'B. Robert singled to right field'"
    },
    {
      "location": {
        "half": "bottom",
        "inning": 5,
        "line_index": 7
      },
      "raw": "Z. Denton struck out swinging.\n                                                                                                                                \t\t\t\t\t(2 out)",
      "reason": "no count-tail on primary clause, and clause did not match any runner rule either: 'Z. Denton struck out swinging'"
    },
    {
      "location": {
        "half": "bottom",
        "inning": 5,
        "line_index": 8
      },
      "raw": "K. Moody flied out to rf.\n                                                                                                                                \t\t\t\t\t(3 out)",
      "reason": "no count-tail on primary clause, and clause did not match any runner rule either: 'K. Moody flied out to rf'"
    },
    {
      "location": {
        "half": "top",
        "inning": 6,
        "line_index": 0
      },
      "raw": "Armstrong II to p for T. Cunningha.",
      "reason": "substitution names did not resolve uniquely on the fielding side: out='T. Cunningha' in='Armstrong II'"
    },
    {
      "location": {
        "half": "top",
        "inning": 6,
        "line_index": 1
      },
      "raw": "C. Wilkerson struck out swinging.\n                                                                                                                                \t\t\t\t\t(1 out)",
      "reason": "no count-tail on primary clause, and clause did not match any runner rule either: 'C. Wilkerson struck out swinging'"
    },
    {
      "location": {
        "half": "top",
        "inning": 6,
        "line_index": 2
      },
      "raw": "M. Rosario struck out swinging.\n                                                                                                                                \t\t\t\t\t(2 out)",
      "reason": "no count-tail on primary clause, and clause did not match any runner rule either: 'M. Rosario struck out swinging'"
    },
    {
      "location": {
        "half": "top",
        "inning": 6,
        "line_index": 3
      },
      "raw": "N. Klemp homered to right field, RBI.",
      "reason": "no count-tail on primary clause, and clause did not match any runner rule either: 'N. Klemp homered to right field, RBI'"
    },
    {
      "location": {
        "half": "top",
        "inning": 6,
        "line_index": 4
      },
      "raw": "A. Fogel walked.",
      "reason": "no count-tail on primary clause, and clause did not match any runner rule either: 'A. Fogel walked'"
    },
    {
      "location": {
        "half": "bottom",
        "inning": 6,
        "line_index": 0
      },
      "raw": "J. Johnson grounded out to 3b.\n                                                                                                                                \t\t\t\t\t(1 out)",
      "reason": "no count-tail on primary clause, and clause did not match any runner rule either: 'J. Johnson grounded out to 3b'"
    },
    {
      "location": {
        "half": "bottom",
        "inning": 6,
        "line_index": 1
      },
      "raw": "Q. Landis flied out to rf.\n                                                                                                                                \t\t\t\t\t(2 out)",
      "reason": "no count-tail on primary clause, and clause did not match any runner rule either: 'Q. Landis flied out to rf'"
    },
    {
      "location": {
        "half": "bottom",
        "inning": 6,
        "line_index": 2
      },
      "raw": "T. McKenzie grounded out to 3b.\n                                                                                                                                \t\t\t\t\t(3 out)",
      "reason": "no count-tail on primary clause, and clause did not match any runner rule either: 'T. McKenzie grounded out to 3b'"
    },
    {
      "location": {
        "half": "top",
        "inning": 7,
        "line_index": 1
      },
      "raw": "L. Barry walked.",
      "reason": "no count-tail on primary clause, and clause did not match any runner rule either: 'L. Barry walked'"
    },
    {
      "location": {
        "half": "top",
        "inning": 7,
        "line_index": 2
      },
      "raw": "J. Piatkiewi grounded into double play 3b to 2b to 1b; L. Barry out on the play.\n                                                                                                                                                                                                                \t\t\t\t\t(2 out)",
      "reason": "no count-tail on primary clause, and clause did not match any runner rule either: 'J. Piatkiewi grounded into double play 3b to 2b to 1b'"
    },
    {
      "location": {
        "half": "top",
        "inning": 7,
        "line_index": 3
      },
      "raw": "T. Smith popped out to 1b.\n                                                                                                                                \t\t\t\t\t(3 out)",
      "reason": "no count-tail on primary clause, and clause did not match any runner rule either: 'T. Smith popped out to 1b'"
    },
    {
      "location": {
        "half": "bottom",
        "inning": 7,
        "line_index": 1
      },
      "raw": "O. Veloz lined out to ss.\n                                                                                                                                \t\t\t\t\t(1 out)",
      "reason": "no count-tail on primary clause, and clause did not match any runner rule either: 'O. Veloz lined out to ss'"
    },
    {
      "location": {
        "half": "bottom",
        "inning": 7,
        "line_index": 2
      },
      "raw": "M. Fabian hit by pitch.",
      "reason": "no count-tail on primary clause, and clause did not match any runner rule either: 'M. Fabian hit by pitch'"
    },
    {
      "location": {
        "half": "bottom",
        "inning": 7,
        "line_index": 3
      },
      "raw": "E. Pagani singled to center field; M. Fabian advanced to second.",
      "reason": "no count-tail on primary clause, and clause did not match any runner rule either: 'E. Pagani singled to center field'"
    },
    {
      "location": {
        "half": "bottom",
        "inning": 7,
        "line_index": 4
      },
      "raw": "B. Robert singled to center field, RBI; E. Pagani advanced to third; M. Fabian scored.",
      "reason": "no count-tail on primary clause, and clause did not match any runner rule either: 'B. Robert singled to center field, RBI'"
    },
    {
      "location": {
        "half": "bottom",
        "inning": 7,
        "line_index": 5
      },
      "raw": "B. Robert stole second, advanced to third on an error by c; E. Pagani stole home.",
      "reason": "runner clause name did not resolve uniquely"
    },
    {
      "location": {
        "half": "bottom",
        "inning": 7,
        "line_index": 6
      },
      "raw": "Z. Denton popped up to ss.\n                                                                                                                                \t\t\t\t\t(2 out)",
      "reason": "no count-tail on primary clause, and clause did not match any runner rule either: 'Z. Denton popped up to ss'"
    },
    {
      "location": {
        "half": "bottom",
        "inning": 7,
        "line_index": 7
      },
      "raw": "K. Moody flied out to rf.\n                                                                                                                                \t\t\t\t\t(3 out)",
      "reason": "no count-tail on primary clause, and clause did not match any runner rule either: 'K. Moody flied out to rf'"
    },
    {
      "location": {
        "half": "top",
        "inning": 8,
        "line_index": 0
      },
      "raw": "C. Perez walked.",
      "reason": "no count-tail on primary clause, and clause did not match any runner rule either: 'C. Perez walked'"
    },
    {
      "location": {
        "half": "top",
        "inning": 8,
        "line_index": 1
      },
      "raw": "C. Wilkerson homered to right center, 2 RBI; C. Perez scored.",
      "reason": "no count-tail on primary clause, and clause did not match any runner rule either: 'C. Wilkerson homered to right center, 2 RBI'"
    },
    {
      "location": {
        "half": "top",
        "inning": 8,
        "line_index": 2
      },
      "raw": "M. Rosario singled to center field.",
      "reason": "no count-tail on primary clause, and clause did not match any runner rule either: 'M. Rosario singled to center field'"
    },
    {
      "location": {
        "half": "top",
        "inning": 8,
        "line_index": 3
      },
      "raw": "N. Klemp struck out looking.\n                                                                                                                                \t\t\t\t\t(1 out)",
      "reason": "no count-tail on primary clause, and clause did not match any runner rule either: 'N. Klemp struck out looking'"
    },
    {
      "location": {
        "half": "top",
        "inning": 8,
        "line_index": 4
      },
      "raw": "A. Fogel lined out to cf.\n                                                                                                                                \t\t\t\t\t(2 out)",
      "reason": "no count-tail on primary clause, and clause did not match any runner rule either: 'A. Fogel lined out to cf'"
    },
    {
      "location": {
        "half": "top",
        "inning": 8,
        "line_index": 5
      },
      "raw": "C. Gordon popped up to 3b.\n                                                                                                                                \t\t\t\t\t(3 out)",
      "reason": "no count-tail on primary clause, and clause did not match any runner rule either: 'C. Gordon popped up to 3b'"
    },
    {
      "location": {
        "half": "bottom",
        "inning": 8,
        "line_index": 1
      },
      "raw": "J. Johnson grounded out to 2b.\n                                                                                                                                \t\t\t\t\t(1 out)",
      "reason": "no count-tail on primary clause, and clause did not match any runner rule either: 'J. Johnson grounded out to 2b'"
    },
    {
      "location": {
        "half": "bottom",
        "inning": 8,
        "line_index": 2
      },
      "raw": "Q. Landis grounded out to ss.\n                                                                                                                                \t\t\t\t\t(2 out)",
      "reason": "no count-tail on primary clause, and clause did not match any runner rule either: 'Q. Landis grounded out to ss'"
    },
    {
      "location": {
        "half": "bottom",
        "inning": 8,
        "line_index": 3
      },
      "raw": "T. McKenzie singled to shortstop.",
      "reason": "no count-tail on primary clause, and clause did not match any runner rule either: 'T. McKenzie singled to shortstop'"
    },
    {
      "location": {
        "half": "bottom",
        "inning": 8,
        "line_index": 4
      },
      "raw": "O. Veloz reached first on an error by 3b; T. McKenzie advanced to third.",
      "reason": "no count-tail on primary clause, and clause did not match any runner rule either: 'O. Veloz reached first on an error by 3b'"
    },
    {
      "location": {
        "half": "bottom",
        "inning": 8,
        "line_index": 5
      },
      "raw": "M. Martinez pinch ran for O. Veloz.",
      "reason": "no count-tail on primary clause, and clause did not match any runner rule either: 'M. Martinez pinch ran for O. Veloz'"
    },
    {
      "location": {
        "half": "bottom",
        "inning": 8,
        "line_index": 7
      },
      "raw": "M. Fabian lined out to cf.\n                                                                                                                                \t\t\t\t\t(3 out)",
      "reason": "no count-tail on primary clause, and clause did not match any runner rule either: 'M. Fabian lined out to cf'"
    },
    {
      "location": {
        "half": "top",
        "inning": 9,
        "line_index": 0
      },
      "raw": "O. Veloz to c for M. Martinez.",
      "reason": "no count-tail on primary clause, and clause did not match any runner rule either: 'O. Veloz to c for M. Martinez'"
    },
    {
      "location": {
        "half": "top",
        "inning": 9,
        "line_index": 2
      },
      "raw": "L. Barry struck out looking.\n                                                                                                                                \t\t\t\t\t(1 out)",
      "reason": "no count-tail on primary clause, and clause did not match any runner rule either: 'L. Barry struck out looking'"
    },
    {
      "location": {
        "half": "top",
        "inning": 9,
        "line_index": 3
      },
      "raw": "J. Piatkiewi walked.",
      "reason": "no count-tail on primary clause, and clause did not match any runner rule either: 'J. Piatkiewi walked'"
    },
    {
      "location": {
        "half": "top",
        "inning": 9,
        "line_index": 4
      },
      "raw": "R. Pena pinch hit for T. Smith.",
      "reason": "no count-tail on primary clause, and clause did not match any runner rule either: 'R. Pena pinch hit for T. Smith'"
    },
    {
      "location": {
        "half": "top",
        "inning": 9,
        "line_index": 5
      },
      "raw": "R. Pena struck out looking; J. Piatkiewi stole second.\n                                                                                                                                                                                    \t\t\t\t\t(2 out)",
      "reason": "no count-tail on primary clause, and clause did not match any runner rule either: 'R. Pena struck out looking'"
    },
    {
      "location": {
        "half": "top",
        "inning": 9,
        "line_index": 6
      },
      "raw": "C. Perez singled to center field, RBI; J. Piatkiewi scored.",
      "reason": "no count-tail on primary clause, and clause did not match any runner rule either: 'C. Perez singled to center field, RBI'"
    },
    {
      "location": {
        "half": "top",
        "inning": 9,
        "line_index": 7
      },
      "raw": "C. Wilkerson lined out to 2b.\n                                                                                                                                \t\t\t\t\t(3 out)",
      "reason": "no count-tail on primary clause, and clause did not match any runner rule either: 'C. Wilkerson lined out to 2b'"
    },
    {
      "location": {
        "half": "bottom",
        "inning": 9,
        "line_index": 0
      },
      "raw": "R. Pena to 1b.",
      "reason": "no count-tail on primary clause, and clause did not match any runner rule either: 'R. Pena to 1b'"
    },
    {
      "location": {
        "half": "bottom",
        "inning": 9,
        "line_index": 1
      },
      "raw": "E. Pagani struck out swinging.\n                                                                                                                                \t\t\t\t\t(1 out)",
      "reason": "no count-tail on primary clause, and clause did not match any runner rule either: 'E. Pagani struck out swinging'"
    },
    {
      "location": {
        "half": "bottom",
        "inning": 9,
        "line_index": 2
      },
      "raw": "B. Robert grounded out to ss.\n                                                                                                                                \t\t\t\t\t(2 out)",
      "reason": "no count-tail on primary clause, and clause did not match any runner rule either: 'B. Robert grounded out to ss'"
    },
    {
      "location": {
        "half": "bottom",
        "inning": 9,
        "line_index": 3
      },
      "raw": "Z. Denton struck out swinging.\n                                                                                                                                \t\t\t\t\t(3 out)",
      "reason": "no count-tail on primary clause, and clause did not match any runner rule either: 'Z. Denton struck out swinging'"
    }
  ]
}
